MANIFEST.in
README.md
requirements.txt
setup.py
fcis/__init__.py
fcis/mask.py
fcis/utils.py
fcis.egg-info/PKG-INFO
fcis.egg-info/SOURCES.txt
fcis.egg-info/dependency_links.txt
fcis.egg-info/requires.txt
fcis.egg-info/top_level.txt
fcis/dataset/__init__.py
fcis/dataset/convert.py
fcis/datasets/__init__.py
fcis/datasets/coco/__init__.py
fcis/datasets/coco/coco_instance_segmentation_dataset.py
fcis/datasets/coco/coco_utils.py
fcis/datasets/sbd/__init__.py
fcis/datasets/sbd/sbd_instance_segmentation_dataset.py
fcis/datasets/sbd/sbd_utils.py
fcis/datasets/voc/__init__.py
fcis/datasets/voc/voc_instance_segmentation_dataset.py
fcis/datasets/voc/voc_utils.py
fcis/evaluations/__init__.py
fcis/evaluations/eval_instance_segmentation_coco.py
fcis/evaluations/eval_instance_segmentation_voc.py
fcis/extensions/__init__.py
fcis/extensions/instance_segmentation_coco_evaluator.py
fcis/functions/__init__.py
fcis/functions/psroi_pooling_2d.py
fcis/models/__init__.py
fcis/models/fcis_base.py
fcis/models/fcis_resnet101.py
fcis/models/fcis_train_chain.py
fcis/models/resnet101.py
fcis/models/utils/__init__.py
fcis/models/utils/proposal_target_creator.py
static/coco_example.png
static/original_output.png
static/output.png
static/voc_example.png