Metadata-Version: 1.0
Name: fcis
Version: 2.1.2
Summary: Chainer Implementation of FCIS
Home-page: https://github.com/knorth55/chainer-fcis
Author: Shingo Kitagawa
Author-email: shingogo.5511@gmail.com
License: MIT
Keywords: machine-learning
Platform: UNKNOWN
